understreck/__init__.py
understreck/chunks.py
understreck/exceptions.py
understreck/filter.py
understreck/nested_get.py
understreck/strip.py
understreck-1.0.0.dist-info/AUTHORS.rst
understreck-1.0.0.dist-info/LICENSE
understreck-1.0.0.dist-info/METADATA
understreck-1.0.0.dist-info/WHEEL
understreck-1.0.0.dist-info/top_level.txt
understreck-1.0.0.dist-info/RECORD
