Metadata-Version: 2.1
Name: understreck
Version: 1.0.0
Summary: A collection of nice utility functions for python
Home-page: https://github.com/cfarvidson/understreck
Author: Carl-Fredrik Arvidson
Author-email: carl-fredrik@arvidson.io
License: GNU General Public License v3
Keywords: understreck
Platform: UNKNOWN
Classifier: Development Status :: 5 - Production/Stable
Classifier: Intended Audience :: Developers
Classifier: License :: OSI Approved :: GNU General Public License v3 (GPLv3)
Classifier: Natural Language :: English
Classifier: Programming Language :: Python :: 2
Classifier: Programming Language :: Python :: 2.7
Classifier: Programming Language :: Python :: 3
Classifier: Programming Language :: Python :: 3.4
Classifier: Programming Language :: Python :: 3.5
Classifier: Programming Language :: Python :: 3.6
Classifier: Programming Language :: Python :: 3.7
Classifier: Programming Language :: Python :: 3.8
Classifier: Programming Language :: Python :: Implementation :: PyPy
